aoxvli/__init__.py
aoxvli/cooperate/__init__.py
aoxvli/cooperate/coop.py
aoxvli/mono/TB_mono_MoS2_exciton.py
aoxvli/mono/TB_mono_tmds.py
aoxvli/mono/__init__.py
aoxvli/mono/graphene_haldane.py
aoxvli/public/__init__.py
aoxvli/public/consts.py
aoxvli/public/method.py
aoxvli/tri/ABC_tri_gra.py
aoxvli/tri/__init__.py
aoxvli/twisted_mat/__init__.py
aoxvli/twisted_mat/twisted_MoTe2.py
aoxvli/twisted_mat/twisted_bi_gra.py
aoxvli/twisted_mat/twisted_tri_gra.py
aoxvli-1.0.5.dist-info/METADATA
aoxvli-1.0.5.dist-info/WHEEL
aoxvli-1.0.5.dist-info/top_level.txt
aoxvli-1.0.5.dist-info/RECORD
